{
  "project_info": {
    "project_number": "818434110540",
    "project_id": "flutter-exercise-81b3c",
    "storage_bucket": "flutter-exercise-81b3c.firebasestorage.app"
  },
  "client": [
    {
      "client_info": {
        "mobilesdk_app_id": "1:818434110540:android:7d53d4d88ef618b9a030e9",
        "android_client_info": {
          "package_name": "com.example.flutter_project"
        }
      },
      "oauth_client": [
        {
          "client_id": "818434110540-bneri9ntcmeamuh1m83qjtskedj9evdc.apps.googleusercontent.com",
          "client_type": 3
        }
      ],
      "api_key": [
        {
          "current_key": "AIzaSyBMPEjWSKgbb9_pRVMSnOguQwIxCZg8tIc"
        }
      ],
      "services": {
        "appinvite_service": {
          "other_platform_oauth_client": [
            {
              "client_id": "818434110540-bneri9ntcmeamuh1m83qjtskedj9evdc.apps.googleusercontent.com",
              "client_type": 3
            }
          ]
        }
      }
    }
  ],
  "configuration_version": "1"
}